README.md
license.txt
setup.cfg
setup.py
test/ciao.py
test/filters_check.py
test/page_check.py
test/search_check.py
test/seeds_peer_sort_check.py
test/size_check.py
test/test.py
test/user_input_torrentz.py
torrents2py/__init__.py
torrents2py/main.py
torrents2py/utils.py
torrents2py.egg-info/PKG-INFO
torrents2py.egg-info/SOURCES.txt
torrents2py.egg-info/dependency_links.txt
torrents2py.egg-info/requires.txt
torrents2py.egg-info/top_level.txt